[
    {
        "id": "rz-1",
        "name": "Red Sea / Gulf of Aden",
        "type": "war_risk",
        "region": "Middle East",
        "severity": "Critical",
        "description": "Active Houthi attacks on commercial vessels",
        "active": true
    },
    {
        "id": "rz-2",
        "name": "Gulf of Guinea",
        "type": "piracy",
        "region": "West Africa",
        "severity": "High",
        "description": "Piracy and armed robbery incidents",
        "active": true
    },
    {
        "id": "rz-3",
        "name": "Black Sea — Western",
        "type": "war_risk",
        "region": "Eastern Europe",
        "severity": "Critical",
        "description": "Active conflict zone, mine risk",
        "active": true
    },
    {
        "id": "rz-4",
        "name": "Strait of Hormuz",
        "type": "restricted",
        "region": "Middle East",
        "severity": "High",
        "description": "Geopolitical tensions, vessel seizure risk",
        "active": true
    }
]